[
    {
        "nombre": "Jugador1",
        "contraseña": "Jugador1",
        "aciertos": 8,
        "errores": 2,
        "tiempo_total": 52.6,
        "partidas": 1,
        "mejor_puntos": 2,
        "mejor_tiempo": 52.6,
        "mejor_dificultad": "Difícil",
        "mejor_categoria": "Entretenimiento"
    },
    {
        "nombre": "Jugador2",
        "contraseña": "Jugador2",
        "aciertos": 8,
        "errores": 2,
        "tiempo_total": 52.6,
        "partidas": 1,
        "mejor_puntos": 2,
        "mejor_tiempo": 52.6,
        "mejor_dificultad": "Difícil",
        "mejor_categoria": "Entretenimiento"
    },
    {
        "nombre": "Jugador3",
        "contraseña": "Jugador3",
        "aciertos": 8,
        "errores": 2,
        "tiempo_total": 52.6,
        "partidas": 1,
        "mejor_puntos": 2,
        "mejor_tiempo": 52.6,
        "mejor_dificultad": "Difícil",
        "mejor_categoria": "Entretenimiento"
    }
]